mmar_mcli/__init__.py
mmar_mcli/io_aiohttp.py
mmar_mcli/maestro_client.py
mmar_mcli/maestro_client_dummy.py
mmar_mcli/models.py
mmar_mcli/utils.py
mmar_mcli-1.0.13.dist-info/licenses/LICENSE
mmar_mcli-1.0.13.dist-info/WHEEL
mmar_mcli-1.0.13.dist-info/METADATA
mmar_mcli-1.0.13.dist-info/RECORD
