Metadata-Version: 2.4
Name: mmar-mcli
Version: 1.0.13
Summary: Client to Maestro
Keywords: 
Author: tagin
Author-email: tagin <tagin@airi.net>
License-Expression: MIT
License-File: LICENSE
Classifier: Development Status :: 4 - Beta
Classifier: Intended Audience :: Developers
Classifier: Programming Language :: Python
Classifier: Programming Language :: Python :: 3
Classifier: Programming Language :: Python :: 3 :: Only
Classifier: Programming Language :: Python :: 3.12
Classifier: Programming Language :: Python :: 3.13
Classifier: Programming Language :: Python :: 3.14
Classifier: Topic :: Documentation
Classifier: Topic :: Software Development
Classifier: Topic :: Utilities
Classifier: Typing :: Typed
Requires-Dist: aiohttp==3.12.15
Requires-Dist: loguru==0.7.3
Requires-Dist: mmar-mapi~=1.4.2
Requires-Dist: mmar-utils~=1.1.16
Requires-Python: >=3.12
